{"guide_markdown.md":"3Dp46vEA","guide_getting-started.md":"C9_qrZB0","tools_docker.md":"DM0cR-T5","technology_pinia.md":"CoIeyn4W","technology_electronjs.md":"T4XPTHVI","index.md":"Cs-Z81zT","code-snippet_html.md":"Cqm0HXIw","code-snippet_demo.md":"COiQ6GM4","code-snippet_css.md":"C0WWyu92","tools_linux.md":"ZZcnV1zo","tools_nvm.md":"8a-6AQDO","technology_unocss.md":"C0sIzapA","code-snippet_js.md":"CKTdya-z","tools_package.md":"235zvBUU","technology_nuxtjs.md":"CwQff9rR","guide_vitepress.md":"Cw4m5Qw_","tools_pm2.md":"NddscNq6","tools_git.md":"Bv6PHJU1","technology_nestjs.md":"Nw5oWIaR","tools_vscode.md":"Dm5u5EiF","technology_vue.md":"Da9tTaW8","technology_naiveui.md":"oah80taJ"}
